[{"last_rev": 6399, "idx": null, "change_rev": null, "pretty_name": "api.testds.time_create_test_dataset1", "last_err": 0.0, "prev_value": null, "last_value": 0.5695270299911499, "name": "api.testds.time_create_test_dataset1"}, {"last_rev": 6399, "idx": null, "change_rev": null, "pretty_name": "api.testds.time_create_test_dataset2x2", "last_err": 0.0, "prev_value": null, "last_value": 3.816820502281189, "name": "api.testds.time_create_test_dataset2x2"}, {"last_rev": 6399, "idx": null, "change_rev": null, "pretty_name": "core.startup.time_help_np", "last_err": 0.0, "prev_value": null, "last_value": 0.2404334545135498, "name": "core.startup.time_help_np"}, {"last_rev": 6399, "idx": null, "change_rev": null, "pretty_name": "core.startup.time_import", "last_err": 0.0, "prev_value": null, "last_value": 0.10800743103027344, "name": "core.startup.time_import"}, {"last_rev": 6399, "idx": null, "change_rev": null, "pretty_name": "core.startup.time_import_api", "last_err": 0.0, "prev_value": null, "last_value": 0.23189544677734375, "name": "core.startup.time_import_api"}]